{
	"quest_type": "one_choice",
	"option_index": "katakana_aiueo",
	"correct_value": 1,
	"tags": [
		"Illustrator",
		"出力"
	],
	"options": [
		{
			"id": "ア",
			"option_md": "<pre>PDF保存時に「透明効果を保持」を選択</pre>\n",
			"option_html": "<pre>PDF保存時に「透明効果を保持」を選択</pre>\n"
		},
		{
			"id": "イ",
			"option_md": "<pre>エクスポート時に「透明効果オプション」を選択</pre>\n",
			"option_html": "<pre>エクスポート時に「透明効果オプション」を選択</pre>\n"
		},
		{
			"id": "ウ",
			"option_md": "<pre>PDF設定で透明を選択</pre>\n",
			"option_html": "<pre>PDF設定で透明を選択</pre>\n"
		},
		{
			"id": "エ",
			"option_md": "<pre>印刷設定で透明効果を有効にする</pre>\n",
			"option_html": "<pre>印刷設定で透明効果を有効にする</pre>\n"
		}
	]
}