{
	"quest_type": "one_choice",
	"options": [
		{
			"id": "ア",
			"option_md": "<pre>[グラフツール]の[書式]タブから[データラベルのフォント設定]を選ぶ</pre>\n",
			"option_html": "<pre>[グラフツール]の[書式]タブから[データラベルのフォント設定]を選ぶ</pre>\n"
		},
		{
			"id": "イ",
			"option_md": "<pre>[挿入]タブの[テキスト]から[フォントサイズ]を選ぶ</pre>\n",
			"option_html": "<pre>[挿入]タブの[テキスト]から[フォントサイズ]を選ぶ</pre>\n"
		},
		{
			"id": "ウ",
			"option_md": "<pre>[グラフ]を右クリックして[データラベルの書式設定]を選び、フォントサイズを変更する</pre>\n",
			"option_html": "<pre>[グラフ]を右クリックして[データラベルの書式設定]を選び、フォントサイズを変更する</pre>\n"
		},
		{
			"id": "エ",
			"option_md": "<pre>[グラフツール]の[デザイン]タブから[フォントサイズの変更]を選ぶ</pre>\n",
			"option_html": "<pre>[グラフツール]の[デザイン]タブから[フォントサイズの変更]を選ぶ</pre>\n"
		}
	]
}