{
	"quest_type": "one_choice",
	"option_index": "katakana_aiueo",
	"correct_value": 3,
	"tags": [
		"Photoshop"
	],
	"options": [
		{
			"id": "ア",
			"option_md": "<pre>レイヤーを非表示にする</pre>\n",
			"option_html": "<pre>レイヤーを非表示にする</pre>\n"
		},
		{
			"id": "イ",
			"option_md": "<pre>ファイルを保存する</pre>\n",
			"option_html": "<pre>ファイルを保存する</pre>\n"
		},
		{
			"id": "ウ",
			"option_md": "<pre>ドキュメントを閉じる</pre>\n",
			"option_html": "<pre>ドキュメントを閉じる</pre>\n"
		},
		{
			"id": "エ",
			"option_md": "<pre>新規ドキュメントを作成する</pre>\n",
			"option_html": "<pre>新規ドキュメントを作成する</pre>\n"
		}
	]
}