{
	"quest_type": "one_choice",
	"options": [
		{
			"id": "ア",
			"option_md": "<pre>Photoshop 5.0</pre>\n",
			"option_html": "<pre>Photoshop 5.0</pre>\n"
		},
		{
			"id": "イ",
			"option_md": "<pre>Photoshop 6.0</pre>\n",
			"option_html": "<pre>Photoshop 6.0</pre>\n"
		},
		{
			"id": "ウ",
			"option_md": "<pre>Photoshop 7.0</pre>\n",
			"option_html": "<pre>Photoshop 7.0</pre>\n"
		},
		{
			"id": "エ",
			"option_md": "<pre>Photoshop CS</pre>\n",
			"option_html": "<pre>Photoshop CS</pre>\n"
		}
	]
}