{
	"quest_type": "one_choice",
	"option_index": "katakana_aiueo",
	"correct_value": 2,
	"tags": [
		"ストラテジ系",
		"法務",
		"セキュリティ関連法規"
	],
	"options": [
		{
			"id": "ア",
			"option_md": "電子署名法\n",
			"option_html": "<p>電子署名法</p>\n"
		},
		{
			"id": "イ",
			"option_md": "不正アクセス禁止法\n",
			"option_html": "<p>不正アクセス禁止法</p>\n"
		},
		{
			"id": "ウ",
			"option_md": "特定秘密保護法\n",
			"option_html": "<p>特定秘密保護法</p>\n"
		},
		{
			"id": "エ",
			"option_md": "情報公開法\n",
			"option_html": "<p>情報公開法</p>\n"
		}
	]
}