{
	"quest_type": "one_choice",
	"option_index": "katakana_aiueo",
	"correct_value": 2,
	"tags": [
		"Photoshop",
		"テキスト・タイポグラフィ"
	],
	"options": [
		{
			"id": "ア",
			"option_md": "<pre>「レイヤースタイル」の「文字アニメーション」を使う</pre>\n",
			"option_html": "<pre>「レイヤースタイル」の「文字アニメーション」を使う</pre>\n"
		},
		{
			"id": "イ",
			"option_md": "<pre>「時間軸」パネルを使ってアニメーションを設定する</pre>\n",
			"option_html": "<pre>「時間軸」パネルを使ってアニメーションを設定する</pre>\n"
		},
		{
			"id": "ウ",
			"option_md": "<pre>「文字ツール」でアニメーションオプションを設定する</pre>\n",
			"option_html": "<pre>「文字ツール」でアニメーションオプションを設定する</pre>\n"
		},
		{
			"id": "エ",
			"option_md": "<pre>「レイヤーパネル」からアニメーションを追加する</pre>\n",
			"option_html": "<pre>「レイヤーパネル」からアニメーションを追加する</pre>\n"
		}
	]
}