{
	"quest_type": "one_choice",
	"options": [
		{
			"id": "ア",
			"option_md": "<pre>文字 > アウトラインを作成</pre>\n",
			"option_html": "<pre>文字 &gt; アウトラインを作成</pre>\n"
		},
		{
			"id": "イ",
			"option_md": "<pre>文字パネルでアウトラインを作成する</pre>\n",
			"option_html": "<pre>文字パネルでアウトラインを作成する</pre>\n"
		},
		{
			"id": "ウ",
			"option_md": "<pre>オブジェクト > パス > アウトライン化</pre>\n",
			"option_html": "<pre>オブジェクト &gt; パス &gt; アウトライン化</pre>\n"
		},
		{
			"id": "エ",
			"option_md": "<pre>アピアランスパネルでアウトラインを作成</pre>\n",
			"option_html": "<pre>アピアランスパネルでアウトラインを作成</pre>\n"
		}
	]
}