{
	"quest_type": "one_choice",
	"option_index": "katakana_aiueo",
	"correct_value": 2,
	"tags": [
		"Photoshop",
		"ファイル管理・出力"
	],
	"options": [
		{
			"id": "ア",
			"option_md": "<pre>塗りつぶしツール</pre>\n",
			"option_html": "<pre>塗りつぶしツール</pre>\n"
		},
		{
			"id": "イ",
			"option_md": "<pre>グラデーションツール</pre>\n",
			"option_html": "<pre>グラデーションツール</pre>\n"
		},
		{
			"id": "ウ",
			"option_md": "<pre>なげなわツール</pre>\n",
			"option_html": "<pre>なげなわツール</pre>\n"
		},
		{
			"id": "エ",
			"option_md": "<pre>ブラシツール</pre>\n",
			"option_html": "<pre>ブラシツール</pre>\n"
		}
	]
}