{
	"quest_type": "one_choice",
	"option_index": "katakana_aiueo",
	"correct_value": 2,
	"tags": [
		"Excel",
		"基本操作"
	],
	"options": [
		{
			"id": "ア",
			"option_md": "<pre>#</pre>\n",
			"option_html": "<pre>#</pre>\n"
		},
		{
			"id": "イ",
			"option_md": "<pre>$</pre>\n",
			"option_html": "<pre>$</pre>\n"
		},
		{
			"id": "ウ",
			"option_md": "<pre>@</pre>\n",
			"option_html": "<pre>@</pre>\n"
		},
		{
			"id": "エ",
			"option_md": "<pre>%</pre>\n",
			"option_html": "<pre>%</pre>\n"
		}
	]
}